python_skat_webservice/__init__.py
python_skat_webservice/common.py
python_skat_webservice/indkomst_oplysning_person_hent.py
python_skat_webservice/soap_signer.py
python_skat_webservice-0.1.0.dist-info/licenses/LICENSE
python_skat_webservice-0.1.0.dist-info/METADATA
python_skat_webservice-0.1.0.dist-info/WHEEL
python_skat_webservice-0.1.0.dist-info/top_level.txt
python_skat_webservice-0.1.0.dist-info/RECORD
