Metadata-Version: 2.4
Name: python-skat-webservice
Version: 0.1.0
Summary: This project makes it easier to use the SKAT webservices.
Requires-Python: >=3.11
License-File: LICENSE
Requires-Dist: lxml>=5.3.2
Requires-Dist: requests>=2.32.3
Requires-Dist: xmlsec>=1.3.15
Dynamic: license-file
